invalid_scraper/__init__.py
invalid_scraper/__meta__.py
invalid_scraper/cli.py
invalid_scraper/data/hosts.yml
invalid_scraper-0.1.0rc2.dist-info/LICENSE
invalid_scraper-0.1.0rc2.dist-info/METADATA
invalid_scraper-0.1.0rc2.dist-info/WHEEL
invalid_scraper-0.1.0rc2.dist-info/entry_points.txt
invalid_scraper-0.1.0rc2.dist-info/top_level.txt
invalid_scraper-0.1.0rc2.dist-info/RECORD
