Metadata-Version: 2.1
Name: invalid-scraper
Version: 0.1.0rc2
Summary: A tool for finding rov-invalid received routes.
Home-page: https://github.com/wolcomm/invalid-scraper
Author: Ben Maddison
Author-email: benm@workonline.africa
License: MIT
Download-URL: https://github.com/wolcomm/invalid-scraper/0.1.0rc2
Platform: UNKNOWN
Classifier: Development Status :: 4 - Beta
Classifier: Intended Audience :: Developers
Classifier: License :: OSI Approved :: MIT License
Classifier: Topic :: Software Development :: Libraries :: Python Modules
Classifier: Topic :: Internet
Requires-Dist: napalm (<3.0,>=2.4.0)
Requires-Dist: pyyaml (<4.0,>=3.13)
